qodex_cameras/__init__.py
qodex_cameras/functions.py
qodex_cameras/main.py
qodex_cameras/mixins.py
qodex_cameras/settings.py
qodex_cameras/video_saver.py
qodex_cameras/other/__init__.py
qodex_cameras/other/pyhik_mode.py
qodex_cameras/photos/Test.png
qodex_cameras/photos/__init__.py
qodex_cameras/tests/__init__.py
qodex_cameras/tests/main_tests.py
qodex_cameras-2.5.7.dist-info/licenses/LICENSE
qodex_cameras-2.5.7.dist-info/METADATA
qodex_cameras-2.5.7.dist-info/WHEEL
qodex_cameras-2.5.7.dist-info/top_level.txt
qodex_cameras-2.5.7.dist-info/RECORD
