Metadata-Version: 2.4
Name: qodex_cameras
Version: 2.5.7
Author: PunchyArchy
Author-email: ksmdrmvscthny@gmail.com
License-File: LICENSE
Requires-Dist: requests
Requires-Dist: qodex_recognition>=0.1.3
Requires-Dist: pillow
Dynamic: author
Dynamic: author-email
Dynamic: description
Dynamic: license-file
Dynamic: requires-dist
